ec2_task/__init__.py
ec2_task/connect_ec2.py
ec2_task-0.9.dist-info/METADATA
ec2_task-0.9.dist-info/RECORD
ec2_task-0.9.dist-info/WHEEL
ec2_task-0.9.dist-info/top_level.txt
