Metadata-Version: 2.1
Name: ec2-task
Version: 0.9
Summary: A python module to manage AWS EC2 instances.
Home-page: https://github.com/shubhamdipt/aws-ec2-task
Author: Shubham Dipt
Author-email: shubham.dipt@gmail.com
License: MIT License
Requires-Dist: asn1crypto (==0.24.0)
Requires-Dist: bcrypt (==3.1.4)
Requires-Dist: boto3 (==1.7.48)
Requires-Dist: botocore (==1.10.48)
Requires-Dist: cffi (==1.11.5)
Requires-Dist: cryptography (==2.2.2)
Requires-Dist: docutils (==0.14)
Requires-Dist: idna (==2.7)
Requires-Dist: jmespath (==0.9.3)
Requires-Dist: paramiko (==2.4.1)
Requires-Dist: pyasn1 (==0.4.3)
Requires-Dist: pycparser (==2.18)
Requires-Dist: PyNaCl (==1.2.1)
Requires-Dist: python-dateutil (==2.7.3)
Requires-Dist: s3transfer (==0.1.13)
Requires-Dist: six (==1.11.0)
